moroccan_licence_plate/__init__.py
moroccan_licence_plate/inference_utils/__init__.py
moroccan_licence_plate/inference_utils/batching.py
moroccan_licence_plate/inference_utils/tools.py
moroccan_licence_plate/training/__init__.py
moroccan_licence_plate/training/train.py
moroccan_licence_plate/training/model/__init__.py
moroccan_licence_plate/training/model/utils.py
moroccan_licence_plate/training/model/yolo3.py
moroccan_licence_plate/training/synthetic_data/__init__.py
moroccan_licence_plate/training/synthetic_data/classes.py
moroccan_licence_plate/training/synthetic_data/synthesizer.py
moroccan_licence_plate/training/synthetic_data/utils.py
moroccan_licence_plate-0.1.2.dist-info/LICENSE
moroccan_licence_plate-0.1.2.dist-info/METADATA
moroccan_licence_plate-0.1.2.dist-info/WHEEL
moroccan_licence_plate-0.1.2.dist-info/top_level.txt
moroccan_licence_plate-0.1.2.dist-info/RECORD
