Metadata-Version: 2.1
Name: moroccan-licence-plate
Version: 0.1.2
Summary: Detection and recognition of moroccan car licence plates.
Home-page: https://github.com/taoufik1el/plate_characters_detection
Author: Taoufik El Khaouja
Author-email: el1khaouja.taoufik@gmail.com
Classifier: Programming Language :: Python :: 3
Classifier: License :: OSI Approved :: MIT License
Classifier: Operating System :: OS Independent
Requires-Python: >=3.11
License-File: LICENSE
Requires-Dist: pandas~=2.2.2
Requires-Dist: tensorflow~=2.13.1
Requires-Dist: opencv-python~=4.10.0.84
Requires-Dist: pillow~=10.4.0
Requires-Dist: pathlib~=1.0.1
Requires-Dist: tqdm~=4.66.4
Requires-Dist: hydra-core~=1.3.2
Requires-Dist: pre-commit~=3.8.0
